jumplists/__init__.py
jumplists/jumplist.py
jumplists/jumplistitem.py
jumplists-0.1.0.dist-info/LICENSE.txt
jumplists-0.1.0.dist-info/METADATA
jumplists-0.1.0.dist-info/WHEEL
jumplists-0.1.0.dist-info/top_level.txt
jumplists-0.1.0.dist-info/RECORD
