Metadata-Version: 2.1
Name: jumplists
Version: 0.1.0
Summary: Windows Jump Lists helper library
Home-page: https://github.com/qermit/jumplists
Author: Piotr Miedzik
Author-email: qermit@sezamkowa.net
License: MIT
Project-URL: Source, https://github.com/qermit/jumplists
Platform: UNKNOWN
Classifier: Programming Language :: Python :: 3
Classifier: License :: OSI Approved :: MIT License
Classifier: Operating System :: Microsoft :: Windows
Requires-Dist: pywin32
